[
  {
    "number": 2241,
    "title": "is possible to remove system tray?",
    "created_at": "2020-11-11T21:28:16Z",
    "closed_at": "2020-11-11T22:29:28Z",
    "labels": [
      "question"
    ],
    "url": "https://github.com/polybar/polybar/issues/2241",
    "body": "I want to remove the system tray from the polybar, to display only the bar itself.\r\n\r\nIs that possible?\r\n\r\nIf yes, how to make.",
    "comments_url": "https://api.github.com/repos/polybar/polybar/issues/2241/comments",
    "author": "kelvin-hey",
    "comments": [
      {
        "user": "patrick96",
        "created_at": "2020-11-11T22:29:28Z",
        "body": "`tray-position = none`"
      }
    ]
  },
  {
    "number": 1290,
    "title": "polybar order",
    "created_at": "2018-06-19T09:35:28Z",
    "closed_at": "2018-06-19T11:06:02Z",
    "labels": [
      "question"
    ],
    "url": "https://github.com/polybar/polybar/issues/1290",
    "body": "is there a way to control polybar order? lets say i have two polybar's on top, how would i control which would be top and which bottom?\r\n\r\nat the moment its randomly loading their position and i have to reload launch.sh and hope it gets to the right position.",
    "comments_url": "https://api.github.com/repos/polybar/polybar/issues/1290/comments",
    "author": "benbuch",
    "comments": [
      {
        "user": "patrick96",
        "created_at": "2018-06-19T11:06:02Z",
        "body": "There is no built in way. If you put a big enough waiting period between launching the bars, the order \r\nshould always be the same. So you should be able to do that inside the launch script, it depends on the WM though"
      }
    ]
  }
]